{
  "name": "Coverdoption",
  "base": "PersistedModel",
  "idInjection": false,
  "options": {
    "validateUpsert": true
  },
  "mysql": {
    "schema": "dtr_reports",
    "table": "coverdoption"
  },
  "properties": {
    "id": {
      "type": "Number",
      "id": true,
      "required": false,
      "length": null,
      "precision": 10,
      "scale": 0,
      "mysql": {
        "columnName": "id",
        "dataType": "int",
        "dataLength": null,
        "dataPrecision": 10,
        "dataScale": 0,
        "nullable": "N"
      }
    },
    "delta": {
      "type": "String",
      "required": false,
      "length": 50,
      "precision": null,
      "scale": null,
      "mysql": {
        "columnName": "delta",
        "dataType": "varchar",
        "dataLength": 50,
        "dataPrecision": null,
        "dataScale": null,
        "nullable": "N"
      }
    },
    "rid": {
      "type": "Number",
      "required": false,
      "length": 250,
      "precision": null,
      "scale": null,
      "mysql": {
        "columnName": "rid",
        "dataType": "int",
        "dataLength": 250,
        "dataPrecision": null,
        "dataScale": null,
        "nullable": "N"
      }
    },
    "iv": {
      "type": "String",
      "required": false,
      "length": 100,
      "precision": null,
      "scale": null,
      "mysql": {
        "columnName": "iv",
        "dataType": "varchar",
        "dataLength": 100,
        "dataPrecision": null,
        "dataScale": null,
        "nullable": "N"
      }
    },
    "strike": {
      "type": "String",
      "required": false,
      "length": 100,
      "precision": null,
      "scale": null,
      "mysql": {
        "columnName": "strike",
        "dataType": "varchar",
        "dataLength": 100,
        "dataPrecision": null,
        "dataScale": null,
        "nullable": "N"
      }
    },
    "ask": {
      "type": "String",
      "required": false,
      "length": 100,
      "precision": null,
      "scale": null,
      "mysql": {
        "columnName": "ask",
        "dataType": "varchar",
        "dataLength": 100,
        "dataPrecision": null,
        "dataScale": null,
        "nullable": "N"
      }
    },
    "lastPrice": {
      "type": "String",
      "required": false,
      "length": 100,
      "precision": null,
      "scale": null,
      "mysql": {
        "columnName": "lastPrice",
        "dataType": "varchar",
        "dataLength": 100,
        "dataPrecision": null,
        "dataScale": null,
        "nullable": "N"
      }
    },
    "code": {
      "type": "String",
      "required": false,
      "length": 100,
      "precision": null,
      "scale": null,
      "mysql": {
        "columnName": "code",
        "dataType": "varchar",
        "dataLength": 100,
        "dataPrecision": null,
        "dataScale": null,
        "nullable": "N"
      }
    },
    "shortname": {
      "type": "String",
      "required": false,
      "length": 100,
      "precision": null,
      "scale": null,
      "mysql": {
        "columnName": "shortname",
        "dataType": "varchar",
        "dataLength": 100,
        "dataPrecision": null,
        "dataScale": null,
        "nullable": "N"
      }
    },
    "underlying": {
      "type": "String",
      "required": false,
      "length": 100,
      "precision": null,
      "scale": null,
      "mysql": {
        "columnName": "underlying",
        "dataType": "varchar",
        "dataLength": 100,
        "dataPrecision": null,
        "dataScale": null,
        "nullable": "N"
      }
    },
    "type": {
      "type": "String",
      "required": false,
      "length": 100,
      "precision": null,
      "scale": null,
      "mysql": {
        "columnName": "type",
        "dataType": "varchar",
        "dataLength": 100,
        "dataPrecision": null,
        "dataScale": null,
        "nullable": "N"
      }
    },
    "expiration": {
      "type": "String",
      "required": false,
      "length": 100,
      "precision": null,
      "scale": null,
      "mysql": {
        "columnName": "expiration",
        "dataType": "varchar",
        "dataLength": 100,
        "dataPrecision": null,
        "dataScale": null,
        "nullable": "N"
      }
    },
    "actiontype": {
      "type": "String",
      "required": false,
      "length": 100,
      "precision": null,
      "scale": null,
      "mysql": {
        "columnName": "actiontype",
        "dataType": "varchar",
        "dataLength": 100,
        "dataPrecision": null,
        "dataScale": null,
        "nullable": "N"
      }
    },
    "lot": {
      "type": "String",
      "required": false,
      "length": 100,
      "precision": null,
      "scale": null,
      "mysql": {
        "columnName": "lot",
        "dataType": "varchar",
        "dataLength": 100,
        "dataPrecision": null,
        "dataScale": null,
        "nullable": "N"
      }
    }
  },
  "validations": [],
  "relations": {},
  "acls": [],
  "methods": {}
}